bogons/__init__.py
bogons/bogons.py
bogons-1.0.3.dist-info/LICENSE
bogons-1.0.3.dist-info/METADATA
bogons-1.0.3.dist-info/WHEEL
bogons-1.0.3.dist-info/top_level.txt
bogons-1.0.3.dist-info/RECORD
